data_pyetl/__init__.py
data_pyetl/api_helper.py
data_pyetl/connectors.py
data_pyetl/database_helper.py
data_pyetl/file_helper.py
data_pyetl/loggin.py
data_pyetl-1.0.27.dist-info/LICENSE
data_pyetl-1.0.27.dist-info/METADATA
data_pyetl-1.0.27.dist-info/WHEEL
data_pyetl-1.0.27.dist-info/RECORD
